evmscript_parser/__init__.py
evmscript_parser/cli.py
evmscript_parser/package.py
evmscript_parser/core/__init__.py
evmscript_parser/core/decoding.py
evmscript_parser/core/exceptions.py
evmscript_parser/core/script_specification.py
evmscript_parser/core/ABI/__init__.py
evmscript_parser/core/ABI/provider.py
evmscript_parser/core/ABI/storage.py
evmscript_parser/core/ABI/utilities/__init__.py
evmscript_parser/core/ABI/utilities/etherscan.py
evmscript_parser/core/ABI/utilities/local.py
evmscript_parser/core/ABI/utilities/processing.py
evmscript_parser/core/decode/__init__.py
evmscript_parser/core/decode/action.py
evmscript_parser/core/decode/structure.py
evmscript_parser/core/parse/__init__.py
evmscript_parser/core/parse/action.py
evmscript_parser/core/parse/structure.py
evmscript_parser-0.3.5.dist-info/LICENSE
evmscript_parser-0.3.5.dist-info/METADATA
evmscript_parser-0.3.5.dist-info/WHEEL
evmscript_parser-0.3.5.dist-info/entry_points.txt
evmscript_parser-0.3.5.dist-info/top_level.txt
evmscript_parser-0.3.5.dist-info/RECORD
