Metadata-Version: 2.1
Name: evmscript-parser
Version: 0.3.5
Summary: Parser for human-readable decoding of EVM scripts.
Home-page: UNKNOWN
Author: Dmitri Ivakhnenko
Author-email: dmit.ivh@gmail.com
License: UNKNOWN
Platform: UNKNOWN
Requires-Python: >=3.8
License-File: LICENSE
Requires-Dist: requests (~=2.26.0)
Requires-Dist: pysha3 (~=1.0.0)
Requires-Dist: eth-brownie (~=1.16.0)
Requires-Dist: web3 (~=5.23.0)
